agent/AGENT_INSTRUCTIONS.md
agent/__init__.py
agent/server.py
agent/scripts/attach-fabric-git.ps1
agent/scripts/attach-log-analytics.ps1
agent/scripts/attach-nsp.ps1
agent/scripts/check-resource.ps1
agent/scripts/create-devops-branch.ps1
agent/scripts/create-devops-pipeline.ps1
agent/scripts/create-devops-project.ps1
agent/scripts/create-devops-repo.ps1
agent/scripts/create-fabric-workspace.ps1
agent/scripts/create-resourcegroup.ps1
agent/scripts/deploy-bicep.ps1
agent/scripts/deploy-pipeline-yaml.ps1
agent/scripts/list-azure-permissions.ps1
agent/scripts/list-devops-projects.ps1
agent/scripts/list-devops-repos.ps1
agent/scripts/list-fabric-permissions.ps1
agent/scripts/list-resources.ps1
agent/templates/ai-foundry.bicep
agent/templates/ai-search.bicep
agent/templates/azure-key-vaults.bicep
agent/templates/azure-openai.bicep
agent/templates/container-registry.bicep
agent/templates/cosmos-db.bicep
agent/templates/fabric-capacity.bicep
agent/templates/log-analytics.bicep
agent/templates/nsp.bicep
agent/templates/storage-account.bicep
agent/templates/user-assigned-managed-identity.bicep
customazuremcpagent-1.0.1.dist-info/LICENSE
customazuremcpagent-1.0.1.dist-info/METADATA
customazuremcpagent-1.0.1.dist-info/WHEEL
customazuremcpagent-1.0.1.dist-info/entry_points.txt
customazuremcpagent-1.0.1.dist-info/top_level.txt
customazuremcpagent-1.0.1.dist-info/RECORD
